latin_scansion/Makefile
latin_scansion/README.md
latin_scansion/__init__.py
latin_scansion/scan.py
latin_scansion/scansion.proto
latin_scansion/scansion.py
latin_scansion/scansion_pb2.py
latin_scansion/textproto.py
latin_scansion/validate.py
latin_scansion-0.1.3.data/data/LICENSE.txt
latin_scansion-0.1.3.dist-info/METADATA
latin_scansion-0.1.3.dist-info/WHEEL
latin_scansion-0.1.3.dist-info/entry_points.txt
latin_scansion-0.1.3.dist-info/licenses/LICENSE.txt
latin_scansion-0.1.3.dist-info/RECORD
