Metadata-Version: 2.3
Name: latin-scansion
Version: 0.1.3
Summary: Automated Latin scansion
Project-URL: Homepage, https://github.com/CUNY-CL/latin_scansion
Author: Jillian Chang
Author-email: Kyle Gorman <kylebgorman@gmail.com>
License-Expression: Apache-2.0
License-File: LICENSE.txt
Keywords: Latin,computational linguistics,language,natural language processing,phonetics,phonology,speech
Classifier: Development Status :: 4 - Beta
Classifier: Environment :: Console
Classifier: License :: OSI Approved :: Apache Software License
Classifier: Operating System :: OS Independent
Classifier: Programming Language :: Python :: 3
Classifier: Programming Language :: Python :: 3 :: Only
Classifier: Programming Language :: Python :: 3.8
Classifier: Programming Language :: Python :: 3.9
Classifier: Programming Language :: Python :: 3.10
Classifier: Programming Language :: Python :: 3.11
Classifier: Programming Language :: Python :: 3.12
Classifier: Topic :: Text Processing :: Linguistic
Requires-Python: >=3.8
Requires-Dist: protobuf>=3.20.2
